{
  "main": {
    "id": "86a630665a9a6948",
    "type": "split",
    "children": [
      {
        "id": "4ccf4f4c47c78ade",
        "type": "tabs",
        "children": [
          {
            "id": "dfe07cf83a61fd68",
            "type": "leaf",
            "state": {
              "type": "markdown",
              "state": {
                "file": "Estadistica/Unidad 1/003_Gráficos.md",
                "mode": "source",
                "source": true
              }
            }
          }
        ]
      }
    ],
    "direction": "vertical"
  },
  "left": {
    "id": "a8dc019f64bbae36",
    "type": "split",
    "children": [
      {
        "id": "e501acb45d0164db",
        "type": "tabs",
        "children": [
          {
            "id": "9f8000dbc3259bd6",
            "type": "leaf",
            "state": {
              "type": "file-explorer",
              "state": {
                "sortOrder": "alphabetical"
              }
            }
          },
          {
            "id": "dc03ba2f5d4b5eb2",
            "type": "leaf",
            "state": {
              "type": "search",
              "state": {
                "query": "",
                "matchingCase": false,
                "explainSearch": false,
                "collapseAll": false,
                "extraContext": false,
                "sortOrder": "alphabetical"
              }
            }
          },
          {
            "id": "f3981d926b4cbdb9",
            "type": "leaf",
            "state": {
              "type": "recent-files",
              "state": {}
            }
          },
          {
            "id": "ba047cd75694ac43",
            "type": "leaf",
            "state": {
              "type": "bookmarks",
              "state": {}
            }
          }
        ]
      }
    ],
    "direction": "horizontal",
    "width": 300
  },
  "right": {
    "id": "b541469cf90e21c5",
    "type": "split",
    "children": [
      {
        "id": "321704afe111cb80",
        "type": "tabs",
        "children": [
          {
            "id": "ac890b488a9fd193",
            "type": "leaf",
            "state": {
              "type": "backlink",
              "state": {
                "file": "Estadistica/Unidad 1/003_Gráficos.md",
                "collapseAll": false,
                "extraContext": false,
                "sortOrder": "alphabetical",
                "showSearch": false,
                "searchQuery": "",
                "backlinkCollapsed": false,
                "unlinkedCollapsed": true
              }
            }
          },
          {
            "id": "e4a3039309f2995d",
            "type": "leaf",
            "state": {
              "type": "outgoing-link",
              "state": {
                "file": "Estadistica/Unidad 1/003_Gráficos.md",
                "linksCollapsed": false,
                "unlinkedCollapsed": true
              }
            }
          },
          {
            "id": "1aef7a6d24d117e7",
            "type": "leaf",
            "state": {
              "type": "tag",
              "state": {
                "sortOrder": "frequency",
                "useHierarchy": true
              }
            }
          },
          {
            "id": "6769e4b27a6ae830",
            "type": "leaf",
            "state": {
              "type": "outline",
              "state": {
                "file": "Estadistica/Unidad 1/003_Gráficos.md"
              }
            }
          }
        ]
      }
    ],
    "direction": "horizontal",
    "width": 300,
    "collapsed": true
  },
  "left-ribbon": {
    "hiddenItems": {
      "switcher:Open quick switcher": true,
      "graph:Open graph view": false,
      "canvas:Create new canvas": false,
      "daily-notes:Open today's daily note": true,
      "templates:Insert template": true,
      "command-palette:Open command palette": true,
      "markdown-importer:Open format converter": false,
      "workspaces:Manage workspace layouts": false,
      "webpage-html-export:Export Vault to HTML": false
    }
  },
  "active": "dfe07cf83a61fd68",
  "lastOpenFiles": [
    "Estadistica/Unidad 1/004_Medidas_de_resumen.md",
    "Electronica/Primer parcial/006_El_diodo_ideal.md",
    "0media/Electronica/Resistencia.png",
    "0media/Electronica/Diagrama_Intensidad.png",
    "0media/Electronica/Diagrama_FueteVoltaje.png",
    "Estadistica/Unidad 1/003_Gráficos.md",
    "Electronica/Primer parcial/003_Origen_de_la_electrónica.md",
    "Electronica/Primer parcial/005_Conceptos_Importantes.md",
    "0media/Electronica/caracteristica electria.gif",
    "0media/Electronica/medicion_1.webp",
    "0media/Electronica/medicion_2.webp",
    "0media/Electronica/Diodo_2.png",
    "Sistemas/Unidad I/001_Sisema.md",
    "Sistemas/Objetivo general.md",
    "Sistemas/Actividades/01 Actividad.md",
    "0media/Electronica/diodo_anodo&catodo.png",
    "0media/Electronica/ValvulaCheck.png",
    "Sistemas/Actividades",
    "Sistemas/Unidad I/002_Componentes del sistema de producción.md",
    "RedesII/Primer parcial/006_Network_Appliance.md",
    "RedesII/Primer parcial/005_Firewalls.md",
    "RedesII/Pendiente.md",
    "RedesII/Primer parcial/004_Extranets.md",
    "0media/Electronica/Portadores_carga.png",
    "RedesII/Primer parcial/003_Software.md",
    "Estadistica/Unidad 1/001_Conceptos_básicos.md",
    "Estadistica/Unidad 1/002 Organización de datos.md",
    "Electronica/Primer parcial/004_Schrodinger's Formula.md",
    "Estadistica/R/001_Bases_R.md",
    "Estadistica/R/002_Gráficos_.md",
    "RedesII/Primer parcial/002_Intranet.md",
    "Electronica/Primer parcial/001_Tipos_de_Materiales.md",
    "0media/Electronica",
    "Estadistica/R",
    "Estadistica/Unidad 1",
    "Estadistica",
    "Sistemas/UML_Lenguaje_Unificado_de_Modelado.md",
    "0media/Sistemas",
    "0media",
    "RedesII/Primer parcial/001_Intranet_Y_Extranet.md",
    "Electronica/Primer parcial",
    "Electronica",
    "Sistemas/Unidad I",
    "Pendiente.md",
    "Primer parcial/001_Intranet_Y_Extranet.md"
  ]
}